pybeast/__init__.py
pybeast/__main__.py
pybeast/command.py
pybeast/main.py
pybeast/template.py
pybeast-0.4.2.dist-info/METADATA
pybeast-0.4.2.dist-info/WHEEL
pybeast-0.4.2.dist-info/entry_points.txt
pybeast-0.4.2.dist-info/RECORD
