Metadata-Version: 2.1
Name: pybeast
Version: 0.4.2
Summary: 
Author: Wytamma Wirth
Author-email: wytamma.wirth@me.com
Requires-Python: >=3.6.2,<4.0
Classifier: Programming Language :: Python :: 3
Classifier: Programming Language :: Python :: 3.7
Classifier: Programming Language :: Python :: 3.8
Classifier: Programming Language :: Python :: 3.9
Classifier: Programming Language :: Python :: 3.10
Classifier: Programming Language :: Python :: 3.11
Classifier: Programming Language :: Python :: 3.12
Classifier: Programming Language :: Python :: 3.13
Requires-Dist: dynamic-beast (>=1.8.2)
Requires-Dist: typer (>=0.3.2)
